kyberswap_py_sdk/__init__.py
kyberswap_py_sdk/kyberswap_py_sdk.py
kyberswap_py_sdk/abis/erc20.json
kyberswap_py_sdk-0.2.8.dist-info/METADATA
kyberswap_py_sdk-0.2.8.dist-info/WHEEL
kyberswap_py_sdk-0.2.8.dist-info/top_level.txt
kyberswap_py_sdk-0.2.8.dist-info/RECORD
