Metadata-Version: 2.1
Name: kyberswap-py-sdk
Version: 0.2.8
Summary: A Python SDK for the KyberSwap Aggregator API
Home-page: https://github.com/Harsh-Gill/kyberswap_py_sdk
Author: Harsh
Author-email: hssingh@connect.ust.hk
License: UNKNOWN
Platform: UNKNOWN
Classifier: Programming Language :: Python :: 3
Classifier: License :: OSI Approved :: MIT License
Classifier: Operating System :: OS Independent
Requires-Python: >=3.10
Requires-Dist: web3 ==6.20.1
Requires-Dist: eth-account
Requires-Dist: requests
